{
  "type": "mysticalcrops:botanical_ritual_table_craft",
  "ingredients": [
    {
      "item": "mysticalcrops:crystal"
    },
    {
      "item": "mysticalcrops:stone_plate"
    },
    {
      "item": "mysticalcrops:uncommon_essence"
    },
    {
      "item": "mysticalcrops:stone_plate"
    },
    {
      "item": "mysticalcrops:uncommon_essence"
    },
    {
      "item": "mysticalcrops:essence_seeds_tier_2"
    },
    {
      "item": "mysticalcrops:stone_plate"
    },
    {
      "item": "mysticalcrops:uncommon_essence"
    },
    {
      "item": "mysticalcrops:stone_plate"
    }
  ],
  "output": {
    "item": "mysticalcrops:stone_seeds"
  }
}