{
  "type": "mysticalcrops:transform",
  "ingredients": [
    {
            "ingredient": {
        "tag": "c:crystals"
      }
    },
    {
      "ingredient": {
      "item": "mysticalcrops:fire_essence"
      }
    },
    {
            "ingredient": {
        "item": "mysticalcrops:wonderful_essence"
      }
    },
    {
      "ingredient": {
      "item": "mysticalcrops:air_essence"
      }
    },
    {
            "ingredient": {
        "item": "mysticalcrops:wonderful_essence"
      }
    },
    {
            "ingredient": {
        "item": "mysticalcrops:wonderful_craft_seeds"
      }
    },
    {
      "ingredient": {
      "item": "mysticalcrops:stone_plate"
      }
    },
    {
      "ingredient": {
      "item": "mysticalcrops:air_essence"
      }
    },
    {
            "ingredient": {
        "item": "mysticalcrops:wonderful_essence"
      }
    },
    {
      "ingredient": {
      "item": "mysticalcrops:fire_essence"
      }
    }
  ],
  "output": {

    "item": "mysticalcrops:nether_seeds"
  }
}